foliant/preprocessors/csvtables.py
foliantcontrib.csvtables-1.0.2.dist-info/LICENSE
foliantcontrib.csvtables-1.0.2.dist-info/METADATA
foliantcontrib.csvtables-1.0.2.dist-info/WHEEL
foliantcontrib.csvtables-1.0.2.dist-info/top_level.txt
foliantcontrib.csvtables-1.0.2.dist-info/RECORD
