Metadata-Version: 2.1
Name: foliantcontrib.csvtables
Version: 1.0.2
Summary: csv to markdown table convertor.
Home-page: https://github.com/foliant-docs/foliantcontrib.csvtables
Author: Anton Bukhtiyarov
Author-email: apkraft@gmail.com
License: MIT
Platform: any
Classifier: Development Status :: 5 - Production/Stable
Classifier: Environment :: Console
Classifier: Intended Audience :: Developers
Classifier: License :: OSI Approved :: MIT License
Classifier: Operating System :: OS Independent
Classifier: Programming Language :: Python
Classifier: Topic :: Documentation
Classifier: Topic :: Utilities
Requires-Dist: foliant (>=1.0.8)
Requires-Dist: foliantcontrib.utils (>=1.0.2)
